netunicorn/library/__init__.py
netunicorn/library/pipelines/__init__.py
netunicorn/library/pipelines/measurements/__init__.py
netunicorn/library/pipelines/measurements/ookla_speedtest.py
netunicorn/library/pipelines/netflex/__init__.py
netunicorn/library/pipelines/netflex/mlab.py
netunicorn/library/pipelines/netflex/ookla.py
netunicorn/library/pipelines/netflex/utils/__init__.py
netunicorn/library/pipelines/netflex/utils/geolocation.py
netunicorn/library/pipelines/netflex/utils/mlab.py
netunicorn/library/pipelines/netflex/utils/ookla.py
netunicorn/library/pipelines/netflex/utils/payload.py
netunicorn/library/tasks/__init__.py
netunicorn/library/tasks/basic.py
netunicorn/library/tasks/flags.py
netunicorn/library/tasks/tasks_utils.py
netunicorn/library/tasks/capture/__init__.py
netunicorn/library/tasks/capture/tcpdump.py
netunicorn/library/tasks/capture/tshark.py
netunicorn/library/tasks/data_transfer/fetch_data.py
netunicorn/library/tasks/data_transfer/send_data.py
netunicorn/library/tasks/handlers/mlab.py
netunicorn/library/tasks/letsencrypt/__init__.py
netunicorn/library/tasks/letsencrypt/tasks.py
netunicorn/library/tasks/measurements/__init__.py
netunicorn/library/tasks/measurements/flent.py
netunicorn/library/tasks/measurements/iperf3.py
netunicorn/library/tasks/measurements/ndt.py
netunicorn/library/tasks/measurements/ookla_speedtest.py
netunicorn/library/tasks/measurements/ping.py
netunicorn/library/tasks/measurements/alexa/alexa.py
netunicorn/library/tasks/measurements/cloudflare/__init__.py
netunicorn/library/tasks/measurements/cloudflare/speedtest.py
netunicorn/library/tasks/network_attacks/__init__.py
netunicorn/library/tasks/network_attacks/arp/__init__.py
netunicorn/library/tasks/network_attacks/arp/spoof.py
netunicorn/library/tasks/network_attacks/cve202141773/__init__.py
netunicorn/library/tasks/network_attacks/ftp/__init__.py
netunicorn/library/tasks/network_attacks/ftp/brute_force_ftp.py
netunicorn/library/tasks/network_attacks/heartbleed/__init__.py
netunicorn_library-0.4.15.dist-info/METADATA
netunicorn_library-0.4.15.dist-info/WHEEL
netunicorn_library-0.4.15.dist-info/top_level.txt
netunicorn_library-0.4.15.dist-info/RECORD
