Metadata-Version: 2.4
Name: netunicorn-library
Version: 0.4.15
Summary: netunicorn contrib library
Author-email: Sylee Beltiukov <rbeltiukov@ucsb.edu>
License: MIT
Keywords: netunicorn
Classifier: Programming Language :: Python :: 3
Classifier: Programming Language :: Python :: 3.9
Classifier: Programming Language :: Python :: 3.10
Classifier: Programming Language :: Python :: 3.11
Classifier: Programming Language :: Python :: 3.12
Classifier: Programming Language :: Python :: 3.13
Requires-Python: >=3.9
Requires-Dist: netunicorn-base<0.5.0,>=0.4.0
